codepropertygraph/__init__.py
codepropertygraph/engine.py
codepropertygraph-0.1.2.dist-info/METADATA
codepropertygraph-0.1.2.dist-info/WHEEL
codepropertygraph-0.1.2.dist-info/top_level.txt
codepropertygraph-0.1.2.dist-info/RECORD
