Metadata-Version: 2.1
Name: codepropertygraph
Version: 0.1.2
Summary: A Python implementation of a Code Property Graph.
Home-page: https://github.com/markgacoka/codepropertygraph
Author: Gacoka Mbui
Author-email: markgacoka@gmail.com
License: Apache License 2.0
Download-URL: https://github.com/markgacoka/codepropertygraph/releases
Keywords: cybersecurity,static analysis,code tokenization,property graph
Platform: UNKNOWN
Classifier: Development Status :: 1 - Planning
Classifier: Intended Audience :: Developers
Classifier: License :: OSI Approved :: Apache Software License
Classifier: Operating System :: OS Independent
Classifier: Programming Language :: Python :: 3
Classifier: Topic :: Security
Classifier: Topic :: Software Development :: Code Generators
Classifier: Topic :: Software Development :: Libraries :: Python Modules
Requires-Python: >=3.9.0
Requires-Dist: neo4j
Requires-Dist: python-dotenv
Requires-Dist: pytest
